{
  "args": {
    "csv": "results/compare_real_powerlaw_random_walk_with_library.csv",
    "data_dir": "data/real_powerlaw",
    "dataset": "twitter_combined",
    "device": "cuda:0",
    "directed": false,
    "edge_list": null,
    "extension_name": "binary_search_random_walk_ext",
    "extension_verbose": false,
    "force_download": false,
    "graph_name": null,
    "iters": 50,
    "json": "results/compare_real_powerlaw_random_walk_with_library.json",
    "keep_duplicates": false,
    "keep_self_loops": false,
    "linear_threshold": 32,
    "max_raw_edges": null,
    "modes": [
      "library",
      "adaptive"
    ],
    "num_starts": 262144,
    "pq": [
      [
        1.0,
        1.0
      ],
      [
        0.25,
        4.0
      ],
      [
        1.0,
        2.0
      ],
      [
        4.0,
        0.25
      ]
    ],
    "seed": 12345,
    "start_mode": "random",
    "url": null,
    "walk_length": 20,
    "warmup": 10
  },
  "dataset_catalog": {
    "twitter_combined": {
      "description": "SNAP Social circles: Twitter combined ego-network edge list",
      "url": "https://snap.stanford.edu/data/twitter_combined.txt.gz"
    }
  },
  "environment": {
    "cuda_capability": "8.0",
    "cuda_device_name": "NVIDIA A100-PCIE-40GB",
    "cuda_total_memory_gb": 39.516,
    "device": "cuda:0",
    "timestamp": "2026-07-01T08:32:50",
    "torch": "2.11.0+cu128",
    "torch_cluster": "1.6.3+pt211cu128",
    "torch_cuda": "12.8"
  },
  "graph": {
    "avg_degree": 33.01837502767324,
    "degree_max": 3383,
    "degree_mean": 33.01837502767324,
    "degree_min": 1,
    "degree_p50": 15.0,
    "degree_p90": 76.0,
    "degree_p95": 117.0,
    "degree_p99": 264.0,
    "graph_type": "real_power_law",
    "num_edges": 2684592,
    "num_nodes": 81306,
    "parse_stats": {
      "duplicate_edges_removed": 2156896,
      "keep_duplicates": false,
      "make_undirected": true,
      "raw_edges_read": 2420766,
      "skipped_self_loops": 22
    }
  },
  "results": [
    {
      "config": {
        "avg_degree": 33.01837502767324,
        "dataset_source": "https://snap.stanford.edu/data/twitter_combined.txt.gz",
        "degree_max": 3383,
        "degree_mean": 33.01837502767324,
        "degree_p50": 15.0,
        "degree_p90": 76.0,
        "degree_p95": 117.0,
        "degree_p99": 264.0,
        "edge_list": "data/real_powerlaw/twitter_combined.txt.gz",
        "graph_build_seconds": 5.237881276989356,
        "graph_name": "twitter_combined",
        "graph_type": "real_power_law",
        "keep_duplicates": false,
        "linear_threshold": 32,
        "make_undirected": true,
        "num_edges": 2684592,
        "num_nodes": 81306,
        "num_starts": 262144,
        "p": 1.0,
        "q": 1.0,
        "sort_csr_ms": 12.233504295349121,
        "start_mode": "random",
        "walk_length": 20
      },
      "mode": "library",
      "stats": {
        "iters": 50,
        "latency_ms_max": 0.6082559823989868,
        "latency_ms_mean": 0.5986303973197937,
        "latency_ms_min": 0.5959680080413818,
        "latency_ms_p50": 0.5985279977321625,
        "latency_ms_p90": 0.600166380405426,
        "latency_ms_p95": 0.6010879874229431,
        "latency_ms_p99": 0.6047436648607254,
        "latency_ms_std": 0.0019855981078555156,
        "output": [
          {
            "device": "cuda:0",
            "dtype": "torch.int64",
            "shape": [
              262144,
              21
            ]
          },
          {
            "device": "cuda:0",
            "dtype": "torch.int64",
            "shape": [
              262144,
              20
            ]
          }
        ],
        "peak_memory_gb": 0.282797,
        "transitions_per_second_p50": 8759623643.113443,
        "walks_per_second_p50": 437981182.1556722,
        "warmup": 10
      }
    },
    {
      "config": {
        "avg_degree": 33.01837502767324,
        "dataset_source": "https://snap.stanford.edu/data/twitter_combined.txt.gz",
        "degree_max": 3383,
        "degree_mean": 33.01837502767324,
        "degree_p50": 15.0,
        "degree_p90": 76.0,
        "degree_p95": 117.0,
        "degree_p99": 264.0,
        "edge_list": "data/real_powerlaw/twitter_combined.txt.gz",
        "graph_build_seconds": 5.237881276989356,
        "graph_name": "twitter_combined",
        "graph_type": "real_power_law",
        "keep_duplicates": false,
        "linear_threshold": 32,
        "make_undirected": true,
        "num_edges": 2684592,
        "num_nodes": 81306,
        "num_starts": 262144,
        "p": 1.0,
        "q": 1.0,
        "sort_csr_ms": 12.233504295349121,
        "start_mode": "random",
        "walk_length": 20
      },
      "mode": "adaptive",
      "stats": {
        "iters": 50,
        "latency_ms_max": 1.7326079607009888,
        "latency_ms_mean": 1.5403622436523436,
        "latency_ms_min": 1.3742079734802246,
        "latency_ms_p50": 1.6005120277404785,
        "latency_ms_p90": 1.6676864504814148,
        "latency_ms_p95": 1.6845312058925628,
        "latency_ms_p99": 1.728593908548355,
        "latency_ms_std": 0.1235680487834058,
        "output": [
          {
            "device": "cuda:0",
            "dtype": "torch.int64",
            "shape": [
              262144,
              21
            ]
          },
          {
            "device": "cuda:0",
            "dtype": "torch.int64",
            "shape": [
              262144,
              20
            ]
          }
        ],
        "peak_memory_gb": 0.282797,
        "transitions_per_second_p50": 3275751702.660824,
        "walks_per_second_p50": 163787585.1330412,
        "warmup": 10
      }
    },
    {
      "config": {
        "avg_degree": 33.01837502767324,
        "dataset_source": "https://snap.stanford.edu/data/twitter_combined.txt.gz",
        "degree_max": 3383,
        "degree_mean": 33.01837502767324,
        "degree_p50": 15.0,
        "degree_p90": 76.0,
        "degree_p95": 117.0,
        "degree_p99": 264.0,
        "edge_list": "data/real_powerlaw/twitter_combined.txt.gz",
        "graph_build_seconds": 5.237881276989356,
        "graph_name": "twitter_combined",
        "graph_type": "real_power_law",
        "keep_duplicates": false,
        "linear_threshold": 32,
        "make_undirected": true,
        "num_edges": 2684592,
        "num_nodes": 81306,
        "num_starts": 262144,
        "p": 0.25,
        "q": 4.0,
        "sort_csr_ms": 12.233504295349121,
        "start_mode": "random",
        "walk_length": 20
      },
      "mode": "library",
      "stats": {
        "iters": 50,
        "latency_ms_max": 274.2763671875,
        "latency_ms_mean": 204.34898986816407,
        "latency_ms_min": 152.94053649902344,
        "latency_ms_p50": 201.48992156982422,
        "latency_ms_p90": 259.48333740234375,
        "latency_ms_p95": 266.8591598510742,
        "latency_ms_p99": 273.9406884765625,
        "latency_ms_std": 32.79747211008565,
        "output": [
          {
            "device": "cuda:0",
            "dtype": "torch.int64",
            "shape": [
              262144,
              21
            ]
          },
          {
            "device": "cuda:0",
            "dtype": "torch.int64",
            "shape": [
              262144,
              20
            ]
          }
        ],
        "peak_memory_gb": 0.362875,
        "transitions_per_second_p50": 26020557.053932518,
        "walks_per_second_p50": 1301027.852696626,
        "warmup": 10
      }
    },
    {
      "config": {
        "avg_degree": 33.01837502767324,
        "dataset_source": "https://snap.stanford.edu/data/twitter_combined.txt.gz",
        "degree_max": 3383,
        "degree_mean": 33.01837502767324,
        "degree_p50": 15.0,
        "degree_p90": 76.0,
        "degree_p95": 117.0,
        "degree_p99": 264.0,
        "edge_list": "data/real_powerlaw/twitter_combined.txt.gz",
        "graph_build_seconds": 5.237881276989356,
        "graph_name": "twitter_combined",
        "graph_type": "real_power_law",
        "keep_duplicates": false,
        "linear_threshold": 32,
        "make_undirected": true,
        "num_edges": 2684592,
        "num_nodes": 81306,
        "num_starts": 262144,
        "p": 0.25,
        "q": 4.0,
        "sort_csr_ms": 12.233504295349121,
        "start_mode": "random",
        "walk_length": 20
      },
      "mode": "adaptive",
      "stats": {
        "iters": 50,
        "latency_ms_max": 17.117183685302734,
        "latency_ms_mean": 17.04071174621582,
        "latency_ms_min": 16.952320098876953,
        "latency_ms_p50": 17.03321647644043,
        "latency_ms_p90": 17.10622787475586,
        "latency_ms_p95": 17.111040115356445,
        "latency_ms_p99": 17.115678977966308,
        "latency_ms_std": 0.038593019542087006,
        "output": [
          {
            "device": "cuda:0",
            "dtype": "torch.int64",
            "shape": [
              262144,
              21
            ]
          },
          {
            "device": "cuda:0",
            "dtype": "torch.int64",
            "shape": [
              262144,
              20
            ]
          }
        ],
        "peak_memory_gb": 0.282797,
        "transitions_per_second_p50": 307803285.8474918,
        "walks_per_second_p50": 15390164.292374589,
        "warmup": 10
      }
    },
    {
      "config": {
        "avg_degree": 33.01837502767324,
        "dataset_source": "https://snap.stanford.edu/data/twitter_combined.txt.gz",
        "degree_max": 3383,
        "degree_mean": 33.01837502767324,
        "degree_p50": 15.0,
        "degree_p90": 76.0,
        "degree_p95": 117.0,
        "degree_p99": 264.0,
        "edge_list": "data/real_powerlaw/twitter_combined.txt.gz",
        "graph_build_seconds": 5.237881276989356,
        "graph_name": "twitter_combined",
        "graph_type": "real_power_law",
        "keep_duplicates": false,
        "linear_threshold": 32,
        "make_undirected": true,
        "num_edges": 2684592,
        "num_nodes": 81306,
        "num_starts": 262144,
        "p": 1.0,
        "q": 2.0,
        "sort_csr_ms": 12.233504295349121,
        "start_mode": "random",
        "walk_length": 20
      },
      "mode": "library",
      "stats": {
        "iters": 50,
        "latency_ms_max": 27.37664031982422,
        "latency_ms_mean": 26.054246292114257,
        "latency_ms_min": 24.4531192779541,
        "latency_ms_p50": 26.897920608520508,
        "latency_ms_p90": 27.2212984085083,
        "latency_ms_p95": 27.28857660293579,
        "latency_ms_p99": 27.363594226837158,
        "latency_ms_std": 1.189960084463674,
        "output": [
          {
            "device": "cuda:0",
            "dtype": "torch.int64",
            "shape": [
              262144,
              21
            ]
          },
          {
            "device": "cuda:0",
            "dtype": "torch.int64",
            "shape": [
              262144,
              20
            ]
          }
        ],
        "peak_memory_gb": 0.362875,
        "transitions_per_second_p50": 194917669.52197793,
        "walks_per_second_p50": 9745883.476098897,
        "warmup": 10
      }
    },
    {
      "config": {
        "avg_degree": 33.01837502767324,
        "dataset_source": "https://snap.stanford.edu/data/twitter_combined.txt.gz",
        "degree_max": 3383,
        "degree_mean": 33.01837502767324,
        "degree_p50": 15.0,
        "degree_p90": 76.0,
        "degree_p95": 117.0,
        "degree_p99": 264.0,
        "edge_list": "data/real_powerlaw/twitter_combined.txt.gz",
        "graph_build_seconds": 5.237881276989356,
        "graph_name": "twitter_combined",
        "graph_type": "real_power_law",
        "keep_duplicates": false,
        "linear_threshold": 32,
        "make_undirected": true,
        "num_edges": 2684592,
        "num_nodes": 81306,
        "num_starts": 262144,
        "p": 1.0,
        "q": 2.0,
        "sort_csr_ms": 12.233504295349121,
        "start_mode": "random",
        "walk_length": 20
      },
      "mode": "adaptive",
      "stats": {
        "iters": 50,
        "latency_ms_max": 8.357888221740723,
        "latency_ms_mean": 8.314716186523437,
        "latency_ms_min": 8.285183906555176,
        "latency_ms_p50": 8.310784339904785,
        "latency_ms_p90": 8.344780731201173,
        "latency_ms_p95": 8.348774337768555,
        "latency_ms_p99": 8.35688446044922,
        "latency_ms_std": 0.019179553910814343,
        "output": [
          {
            "device": "cuda:0",
            "dtype": "torch.int64",
            "shape": [
              262144,
              21
            ]
          },
          {
            "device": "cuda:0",
            "dtype": "torch.int64",
            "shape": [
              262144,
              20
            ]
          }
        ],
        "peak_memory_gb": 0.282797,
        "transitions_per_second_p50": 630852610.9654852,
        "walks_per_second_p50": 31542630.54827426,
        "warmup": 10
      }
    },
    {
      "config": {
        "avg_degree": 33.01837502767324,
        "dataset_source": "https://snap.stanford.edu/data/twitter_combined.txt.gz",
        "degree_max": 3383,
        "degree_mean": 33.01837502767324,
        "degree_p50": 15.0,
        "degree_p90": 76.0,
        "degree_p95": 117.0,
        "degree_p99": 264.0,
        "edge_list": "data/real_powerlaw/twitter_combined.txt.gz",
        "graph_build_seconds": 5.237881276989356,
        "graph_name": "twitter_combined",
        "graph_type": "real_power_law",
        "keep_duplicates": false,
        "linear_threshold": 32,
        "make_undirected": true,
        "num_edges": 2684592,
        "num_nodes": 81306,
        "num_starts": 262144,
        "p": 4.0,
        "q": 0.25,
        "sort_csr_ms": 12.233504295349121,
        "start_mode": "random",
        "walk_length": 20
      },
      "mode": "library",
      "stats": {
        "iters": 50,
        "latency_ms_max": 11.931648254394531,
        "latency_ms_mean": 11.809914836883545,
        "latency_ms_min": 11.713536262512207,
        "latency_ms_p50": 11.799551963806152,
        "latency_ms_p90": 11.885465908050538,
        "latency_ms_p95": 11.903641271591187,
        "latency_ms_p99": 11.928637437820434,
        "latency_ms_std": 0.05214743777800417,
        "output": [
          {
            "device": "cuda:0",
            "dtype": "torch.int64",
            "shape": [
              262144,
              21
            ]
          },
          {
            "device": "cuda:0",
            "dtype": "torch.int64",
            "shape": [
              262144,
              20
            ]
          }
        ],
        "peak_memory_gb": 0.362875,
        "transitions_per_second_p50": 444328735.1996047,
        "walks_per_second_p50": 22216436.759980235,
        "warmup": 10
      }
    },
    {
      "config": {
        "avg_degree": 33.01837502767324,
        "dataset_source": "https://snap.stanford.edu/data/twitter_combined.txt.gz",
        "degree_max": 3383,
        "degree_mean": 33.01837502767324,
        "degree_p50": 15.0,
        "degree_p90": 76.0,
        "degree_p95": 117.0,
        "degree_p99": 264.0,
        "edge_list": "data/real_powerlaw/twitter_combined.txt.gz",
        "graph_build_seconds": 5.237881276989356,
        "graph_name": "twitter_combined",
        "graph_type": "real_power_law",
        "keep_duplicates": false,
        "linear_threshold": 32,
        "make_undirected": true,
        "num_edges": 2684592,
        "num_nodes": 81306,
        "num_starts": 262144,
        "p": 4.0,
        "q": 0.25,
        "sort_csr_ms": 12.233504295349121,
        "start_mode": "random",
        "walk_length": 20
      },
      "mode": "adaptive",
      "stats": {
        "iters": 50,
        "latency_ms_max": 8.462335586547852,
        "latency_ms_mean": 8.437309455871581,
        "latency_ms_min": 8.41113567352295,
        "latency_ms_p50": 8.436736106872559,
        "latency_ms_p90": 8.456192016601562,
        "latency_ms_p95": 8.459469079971313,
        "latency_ms_p99": 8.461834173202515,
        "latency_ms_std": 0.012202660646920672,
        "output": [
          {
            "device": "cuda:0",
            "dtype": "torch.int64",
            "shape": [
              262144,
              21
            ]
          },
          {
            "device": "cuda:0",
            "dtype": "torch.int64",
            "shape": [
              262144,
              20
            ]
          }
        ],
        "peak_memory_gb": 0.282797,
        "transitions_per_second_p50": 621434632.2541907,
        "walks_per_second_p50": 31071731.612709533,
        "warmup": 10
      }
    }
  ]
}
